vektorplotter/.DS_Store
vektorplotter/README.md
vektorplotter/__main__.py
vektorplotter/calcInputclass.py
vektorplotter/colorAssignclass.py
vektorplotter/lineclass.py
vektorplotter/listclass.py
vektorplotter/maingui.py
vektorplotter/nameAssignclass.py
vektorplotter/objectsToFig.py
vektorplotter/planeclass.py
vektorplotter/poetry.lock
vektorplotter/pointclass.py
vektorplotter/solvers.py
vektorplotter/vector3Dclass.py
vektorplotter-0.1.0.dist-info/WHEEL
vektorplotter-0.1.0.dist-info/METADATA
vektorplotter-0.1.0.dist-info/RECORD
